aiocontext/__about__.py
aiocontext/__init__.py
aiocontext/context.py
aiocontext/errors.py
aiocontext/task_factory.py
aiocontext-0.1.1.dist-info/DESCRIPTION.rst
aiocontext-0.1.1.dist-info/METADATA
aiocontext-0.1.1.dist-info/RECORD
aiocontext-0.1.1.dist-info/WHEEL
aiocontext-0.1.1.dist-info/metadata.json
aiocontext-0.1.1.dist-info/top_level.txt
