Metadata-Version: 2.0
Name: aiocontext
Version: 0.1.1
Summary: Context information storage for asyncio.
Home-page: https://github.com/sqreen/AioContext
Author: Sqreen
Author-email: contact@sqreen.io
License: MIT
Platform: UNKNOWN
Classifier: Intended Audience :: Developers
Classifier: License :: OSI Approved :: MIT License
Classifier: Programming Language :: Python :: 3
Classifier: Programming Language :: Python :: 3.4
Classifier: Programming Language :: Python :: 3.5
Classifier: Programming Language :: Python :: 3.6
Classifier: Programming Language :: Python :: Implementation :: CPython
Classifier: Programming Language :: Python
Classifier: Topic :: Software Development
Requires-Python: >=3.4, <4
